git_word_blame-0.0.7.data/scripts/git-word-blame
gitwordblame/__init__.py
gitwordblame/themes.py
gitwordblame/wikiwho_engine.py
git_word_blame-0.0.7.dist-info/LICENSE
git_word_blame-0.0.7.dist-info/METADATA
git_word_blame-0.0.7.dist-info/WHEEL
git_word_blame-0.0.7.dist-info/top_level.txt
git_word_blame-0.0.7.dist-info/RECORD
