Metadata-Version: 2.1
Name: git-word-blame
Version: 0.0.7
Summary: word-by-word blame for git
Home-page: https://framagit.org/mdamien/git-word-blame/
Author: Damien
Author-email: damien@dam.io
License: GPLv3
Platform: UNKNOWN
Classifier: License :: OSI Approved :: GNU General Public License (GPL)
Classifier: Programming Language :: Python :: 3
Classifier: Programming Language :: Python :: 3.3
Classifier: Programming Language :: Python :: 3.4
Classifier: Programming Language :: Python :: 3.5
Requires-Dist: wikiwho
Requires-Dist: mwpersistence
Requires-Dist: lys
Requires-Dist: GitPython
